beepy/__init__.py
beepy/make_sound.py
beepy-1.0.9.dist-info/licenses/LICENSE.txt
beepy-1.0.9.dist-info/METADATA
beepy-1.0.9.dist-info/WHEEL
beepy-1.0.9.dist-info/top_level.txt
beepy-1.0.9.dist-info/RECORD
