Metadata-Version: 2.4
Name: beepy
Version: 1.0.9
Summary: Play notification sounds.
Home-page: https://github.com/prabeshdhakal/beepy/
Author: Prabesh Dhakal
License: MIT
Keywords: beep notification sound beepr beeper
Classifier: Development Status :: 3 - Alpha
Classifier: Intended Audience :: Developers
Classifier: License :: OSI Approved :: MIT License
Classifier: Natural Language :: English
Classifier: Programming Language :: Python :: 3.7
Classifier: Topic :: Multimedia :: Sound/Audio
Requires-Python: >=3.0
License-File: LICENSE.txt
Requires-Dist: simpleaudio
Dynamic: author
Dynamic: classifier
Dynamic: description
Dynamic: home-page
Dynamic: keywords
Dynamic: license
Dynamic: license-file
Dynamic: requires-dist
Dynamic: requires-python
Dynamic: summary
